api_client_generator/__init__.py
api_client_generator/api_client.py
api_client_generator/mock_generator.py
api_client_generator/async_support/__init__.py
api_client_generator/async_support/async_client.py
api_client_generator/authentication/__init__.py
api_client_generator/authentication/api_key_auth.py
api_client_generator/authentication/auth_handler.py
api_client_generator/authentication/oauth_handler.py
api_client_generator/authentication/openid_connect_handler.py
api_client_generator/generator/__init__.py
api_client_generator/generator/client_generator.py
api_client_generator/generator/method_generator.py
api_client_generator/generator/model_generator.py
api_client_generator/parser/__init__.py
api_client_generator/parser/openapi_parser.py
api_client_generator/parser/swagger_parser.py
api_client_generator/utils/__init__.py
api_client_generator/utils/caching.py
api_client_generator/utils/rate_limiter.py
api_client_generator-0.1.0.dist-info/LICENSE
api_client_generator-0.1.0.dist-info/METADATA
api_client_generator-0.1.0.dist-info/WHEEL
api_client_generator-0.1.0.dist-info/top_level.txt
api_client_generator-0.1.0.dist-info/RECORD
