Metadata-Version: 2.1
Name: api-client-generator
Version: 0.1.0
Summary: Automatically generate Python API clients from OpenAPI specifications
Author-email: Brij Kishore Pandey <brij.pydata@gmail.com>
License: MIT License
Project-URL: Homepage, https://github.com/yourusername/api-client-generator
Project-URL: Bug Tracker, https://github.com/yourusername/api-client-generator/issues
Keywords: api,client,generator,openapi,swagger
Classifier: License :: OSI Approved :: MIT License
Classifier: Programming Language :: Python
Classifier: Programming Language :: Python :: 3
Classifier: Programming Language :: Python :: 3.9
Classifier: Programming Language :: Python :: 3.10
Requires-Python: >=3.9
License-File: LICENSE
Requires-Dist: requests>=2.26.0
Requires-Dist: aiohttp<4.0.0,>=3.7.4
Requires-Dist: jinja2>=3.0.1
Requires-Dist: pyyaml>=6.0
Requires-Dist: jsonschema>=4.4.0
